biotagging/__init__.py
biotagging/cli.py
biotagging/main.py
biotagging/schema/jsonresponse.py
biotagging/services/api.py
biotagging/services/testapi.py
biotagging/utils/bio.py
biotagging/utils/tag_json.py
biotagging/utils/tag_pd.py
biotagging/utils/tokenization.py
biotagging-0.1.0.dist-info/METADATA
biotagging-0.1.0.dist-info/WHEEL
biotagging-0.1.0.dist-info/entry_points.txt
biotagging-0.1.0.dist-info/licenses/LICENSE
biotagging-0.1.0.dist-info/RECORD
