Metadata-Version: 2.4
Name: biotagging
Version: 0.1.0
Summary: A robust Python package for BIO entity tagging with automatic sequence repair and validation
Project-URL: Homepage, https://github.com/yourusername/biotagging
Project-URL: Documentation, https://github.com/yourusername/biotagging#readme
Project-URL: Repository, https://github.com/yourusername/biotagging.git
Project-URL: Issues, https://github.com/yourusername/biotagging/issues
Project-URL: Changelog, https://github.com/yourusername/biotagging/releases
Author-email: biotagging <noreply@biotagging.dev>
Maintainer-email: biotagging <noreply@biotagging.dev>
License: MIT
License-File: LICENSE
Keywords: bio-tagging,entity-extraction,machine-learning,named-entity-recognition,natural-language-processing,nlp,text-processing
Classifier: Development Status :: 4 - Beta
Classifier: Intended Audience :: Developers
Classifier: Intended Audience :: Science/Research
Classifier: License :: OSI Approved :: MIT License
Classifier: Operating System :: OS Independent
Classifier: Programming Language :: Python :: 3
Classifier: Programming Language :: Python :: 3.9
Classifier: Programming Language :: Python :: 3.10
Classifier: Programming Language :: Python :: 3.11
Classifier: Programming Language :: Python :: 3.12
Classifier: Programming Language :: Python :: 3.13
Classifier: Topic :: Scientific/Engineering :: Artificial Intelligence
Classifier: Topic :: Software Development :: Libraries :: Python Modules
Classifier: Topic :: Text Processing :: Linguistic
Requires-Python: >=3.9
Requires-Dist: pandas>=2.0.0
Requires-Dist: pydantic>=2.0.0
Provides-Extra: dev
Requires-Dist: black>=23.0.0; extra == 'dev'
Requires-Dist: flake8>=6.0.0; extra == 'dev'
Requires-Dist: isort>=5.12.0; extra == 'dev'
Requires-Dist: mypy>=1.0.0; extra == 'dev'
Requires-Dist: pytest-cov>=4.0.0; extra == 'dev'
Requires-Dist: pytest>=7.0.0; extra == 'dev'
Provides-Extra: test
Requires-Dist: pytest-cov>=4.0.0; extra == 'test'
Requires-Dist: pytest>=7.0.0; extra == 'test'
